dyf_rs/__init__.py
dyf_rs/__pycache__/__init__.cpython-311.pyc
dyf_rs/__pycache__/__init__.cpython-314.pyc
dyf_rs/_core.cpython-311-darwin.so
dyf_rs-0.4.0.dist-info/METADATA
dyf_rs-0.4.0.dist-info/WHEEL
dyf_rs-0.4.0.dist-info/RECORD
