Metadata-Version: 2.4
Name: dyf-rs
Version: 0.4.0
Classifier: Development Status :: 4 - Beta
Classifier: Intended Audience :: Developers
Classifier: Intended Audience :: Science/Research
Classifier: License :: Other/Proprietary License
Classifier: Programming Language :: Python :: 3
Classifier: Programming Language :: Python :: 3.9
Classifier: Programming Language :: Python :: 3.10
Classifier: Programming Language :: Python :: 3.11
Classifier: Programming Language :: Python :: 3.12
Classifier: Programming Language :: Rust
Classifier: Topic :: Scientific/Engineering :: Artificial Intelligence
Requires-Dist: numpy>=1.20
Requires-Dist: pytest>=7.0 ; extra == 'dev'
Requires-Dist: pyarrow>=10.0 ; extra == 'dev'
Requires-Dist: pyarrow>=10.0 ; extra == 'full'
Requires-Dist: polars>=0.19 ; extra == 'full'
Requires-Dist: scikit-learn>=1.0 ; extra == 'full'
Requires-Dist: sentence-transformers>=2.2 ; extra == 'full'
Provides-Extra: dev
Provides-Extra: full
Summary: Density Yields Features - Rust core for structure discovery in embedding spaces
Keywords: outlier,classification,lsh,pca,embeddings,machine-learning
Author-email: Justin Donaldson <jdonaldson@gmail.com>
License: Proprietary
Requires-Python: >=3.9
Project-URL: Homepage, https://github.com/jdonaldson/dyf
Project-URL: Repository, https://github.com/jdonaldson/dyf
